file_browser_cli/__init__.py
file_browser_cli/__main__.py
file_browser_cli/cli.py
file_browser_cli/file_browser.py
file_browser_cli/py.typed
file_browser_cli-0.1.3.dist-info/METADATA
file_browser_cli-0.1.3.dist-info/WHEEL
file_browser_cli-0.1.3.dist-info/entry_points.txt
file_browser_cli-0.1.3.dist-info/RECORD
