Metadata-Version: 2.4
Name: file-browser-cli
Version: 0.1.3
Summary: 一個基於 Typer 與 Textual 的互動式檔案瀏覽與建立工具，支援 CLI 檔案選擇與自動建立新檔案。
Project-URL: homepage, https://numpy.org
Project-URL: source, https://github.com/ShawnSun1031/file-browser-cli
Project-URL: download, https://pypi.org/project/file-browser-cli/#files
Project-URL: tracker, https://github.com/ShawnSun1031/file-browser-cli/issues
Maintainer-email: ChinHsuan Sun <dicky10311111@gmail.com>
Classifier: Development Status :: 1 - Planning
Classifier: Intended Audience :: Developers
Classifier: Operating System :: MacOS
Classifier: Operating System :: Microsoft :: Windows
Classifier: Operating System :: POSIX
Classifier: Operating System :: Unix
Classifier: Programming Language :: Python
Classifier: Programming Language :: Python :: 3
Classifier: Programming Language :: Python :: 3 :: Only
Classifier: Programming Language :: Python :: 3.9
Classifier: Programming Language :: Python :: 3.10
Classifier: Programming Language :: Python :: 3.11
Classifier: Programming Language :: Python :: 3.12
Classifier: Programming Language :: Python :: 3.13
Classifier: Typing :: Typed
Requires-Python: >=3.9
Requires-Dist: textual-dev>=1.7.0
Requires-Dist: textual>=3.2.0
Requires-Dist: typer>=0.15.3
Provides-Extra: lint
Requires-Dist: flake8>=7.2.0; extra == 'lint'
Provides-Extra: test
Requires-Dist: pytest-asyncio>=0.26.0; extra == 'test'
Requires-Dist: pytest-cov>=6.1.1; extra == 'test'
Requires-Dist: pytest>=8.3.5; extra == 'test'
